execute/__init__.py
execute/execute_javascript.py
wb_execute-0.0.1.dist-info/METADATA
wb_execute-0.0.1.dist-info/WHEEL
wb_execute-0.0.1.dist-info/licenses/LICENSE
wb_execute-0.0.1.dist-info/RECORD
