Metadata-Version: 2.4
Name: wb-execute
Version: 0.0.1
Summary: 
License-File: LICENSE
Author: mathewgeola
Author-email: mathewgeola@gmail.com
Requires-Python: >=3.12
Classifier: Programming Language :: Python :: 3
Classifier: Programming Language :: Python :: 3.12
Classifier: Programming Language :: Python :: 3.13
Classifier: Programming Language :: Python :: 3.14
Requires-Dist: mini-racer (>=0.12.4,<0.13.0)
Requires-Dist: orjson (>=3.11.3,<4.0.0)
Requires-Dist: pyexecjs (>=1.5.1,<2.0.0)
